tidyX/SpacyPreprocessor.py
tidyX/TextPreprocessor.py
tidyX/TextVisualizer.py
tidyX/__init__.py
tidyX/spacy_preprocessor.py
tidyX/text_normalization.py
tidyX/text_preprocessor.py
tidyX/text_visualizer.py
tidyX/word_normalization.py
tidyX/data/Tweets sobre migrantes venezolanos.xlsx
tidyX/data/lda_final_model.html
tidyX/data/lda_tuning_results.csv
tidyX-1.7.1.dist-info/LICENSE.rst
tidyX-1.7.1.dist-info/METADATA
tidyX-1.7.1.dist-info/WHEEL
tidyX-1.7.1.dist-info/top_level.txt
tidyX-1.7.1.dist-info/RECORD
